langflow-streamlit/__main__.py
langflow_streamlit/__main__.py
langflow_streamlit/api/__init__.py
langflow_streamlit/api/streamlit.py
langflow_streamlit/cli.py
langflow_streamlit/managers/__init__.py
langflow_streamlit/managers/api_manager.py
langflow_streamlit/managers/langflow_manager.py
langflow_streamlit/managers/streamlit_manager.py
langflow_streamlit/models/__init__.py
langflow_streamlit/models/chat_message_model.py
langflow_streamlit/models/chat_model.py
langflow_streamlit/templates/__init__.py
langflow_streamlit/templates/chat_template.py
langflow_streamlit/utils/__init__.py
langflow_streamlit/utils/default.py
langflow_streamlit/utils/logger.py
langflow_streamlit/utils/process_utils.py
langflow_streamlit/utils/settings.py
pyproject.toml
langflow_streamlit-0.1.8.dist-info/LICENSE
langflow_streamlit-0.1.8.dist-info/METADATA
langflow_streamlit-0.1.8.dist-info/WHEEL
langflow_streamlit-0.1.8.dist-info/entry_points.txt
langflow_streamlit-0.1.8.dist-info/RECORD
