Metadata-Version: 2.1
Name: langflow-streamlit
Version: 0.1.8
Summary: 
License: MIT
Author: YAITEC
Author-email: contact@yaitec.org
Maintainer: João Pedro M. C. Hluchan
Maintainer-email: berrytern@gmail.com
Requires-Python: >=3.10,<3.13
Classifier: License :: OSI Approved :: MIT License
Classifier: Programming Language :: Python :: 3
Classifier: Programming Language :: Python :: 3.10
Classifier: Programming Language :: Python :: 3.11
Classifier: Programming Language :: Python :: 3.12
Requires-Dist: fastapi (>=0.111.0,<0.112.0)
Requires-Dist: httpx (>=0.27.0,<0.28.0)
Requires-Dist: langchain-core (==0.2.30)
Requires-Dist: langflow (>=1.0.14,<2.0.0)
Requires-Dist: python-dotenv (>=1.0.1,<2.0.0)
Requires-Dist: streamlit (>=1.35.0,<2.0.0)
Requires-Dist: typer (>=0.12.3,<0.13.0)
